ormb/__init__.py
ormb/_api_exceptions.py
ormb/api.py
ormb/bin/CHANGELOG.md
ormb/bin/LICENSE
ormb/bin/README.md
ormb/bin/README_zh.md
ormb/bin/ormb
ormb/bin/ormb-storage-initializer
ormb-0.1.0.dist-info/METADATA
ormb-0.1.0.dist-info/WHEEL
ormb-0.1.0.dist-info/top_level.txt
ormb-0.1.0.dist-info/RECORD
