Metadata-Version: 2.1
Name: ormb
Version: 0.1.0
Summary: ormb warehouse
Home-page: https://github.com/kleveross/ormb
Maintainer: gaocegege, ZhuYuJin
License: UNKNOWN
Project-URL: Documentation, https://github.com/kleveross/ormb/wikis/home
Project-URL: Code, https://github.com/kleveross/ormb
Project-URL: Issue tracker, https://github.com/kleveross/ormb/issues
Platform: UNKNOWN
Requires-Python: >=3.6
